{
  "format": "pencil-node-tree",
  "version": 2,
  "source": {
    "url": "http://127.0.0.1:4176/capture/shadcn/dialog/card-details",
    "selector": "[data-capture='shadcn:dialog:card-details']"
  },
  "stats": {
    "frames": 16,
    "groups": 0,
    "texts": 8,
    "images": 0,
    "gradients": 0,
    "svgGraphics": 2,
    "controls": 0,
    "skipped": 1,
    "skippedSvgInvisible": 0,
    "skippedSvgUnsupported": 0,
    "skippedRoots": {
      "span": 1
    }
  },
  "root": {
    "type": "frame",
    "name": "Captured · Build onboarding flow",
    "layout": "none",
    "x": 0,
    "y": 0,
    "width": 384,
    "height": 301,
    "cornerRadius": 14,
    "fill": {
      "type": "color",
      "color": "#FFFFFF",
      "blendMode": "normal"
    },
    "stroke": "#0A0A0A1A",
    "strokeWidth": 1,
    "strokeAlignment": "inner",
    "children": [
      {
        "type": "frame",
        "name": "Div · dialog-header",
        "layout": "none",
        "layoutPosition": "absolute",
        "x": 16,
        "y": 16,
        "width": 352,
        "height": 44,
        "cornerRadius": 0,
        "children": [
          {
            "type": "frame",
            "name": "H2 · dialog-title",
            "layout": "none",
            "layoutPosition": "absolute",
            "x": 0,
            "y": 0,
            "width": 352,
            "height": 16,
            "cornerRadius": 0,
            "children": [
              {
                "type": "text",
                "name": "H2 · dialog-title · Text",
                "layoutPosition": "absolute",
                "x": 0,
                "y": -3,
                "textGrowth": "auto",
                "content": "Build onboarding flow",
                "fill": "#0A0A0A",
                "fontFamily": "Inter",
                "fontSize": 16,
                "fontWeight": "500",
                "fontStyle": "normal",
                "lineHeight": 1,
                "textAlign": "left",
                "textAlignVertical": "top"
              }
            ]
          },
          {
            "type": "frame",
            "name": "P · dialog-description",
            "layout": "none",
            "layoutPosition": "absolute",
            "x": 0,
            "y": 24,
            "width": 352,
            "height": 20,
            "cornerRadius": 0,
            "children": [
              {
                "type": "text",
                "name": "P · dialog-description · Text",
                "layoutPosition": "absolute",
                "x": 0,
                "y": 1,
                "textGrowth": "auto",
                "content": "Review the card details before saving your changes.",
                "fill": "#737373",
                "fontFamily": "Inter",
                "fontSize": 14,
                "fontWeight": "400",
                "fontStyle": "normal",
                "lineHeight": 1.429,
                "textAlign": "left",
                "textAlignVertical": "top"
              }
            ]
          }
        ]
      },
      {
        "type": "frame",
        "name": "Div",
        "layout": "none",
        "layoutPosition": "absolute",
        "x": 16,
        "y": 76,
        "width": 352,
        "height": 144,
        "cornerRadius": 0,
        "children": [
          {
            "type": "frame",
            "name": "Div",
            "layout": "none",
            "layoutPosition": "absolute",
            "x": 0,
            "y": 0,
            "width": 352,
            "height": 66,
            "cornerRadius": 10,
            "stroke": "#E5E5E5",
            "strokeWidth": 1,
            "strokeAlignment": "inner",
            "children": [
              {
                "type": "frame",
                "name": "Span · Owner",
                "layout": "none",
                "layoutPosition": "absolute",
                "x": 13,
                "y": 14,
                "width": 42.266,
                "height": 18,
                "cornerRadius": 0,
                "children": [
                  {
                    "type": "text",
                    "name": "Span · Owner · Text",
                    "layoutPosition": "absolute",
                    "x": 0,
                    "y": 0,
                    "textGrowth": "auto",
                    "content": "Owner",
                    "fill": "#737373",
                    "fontFamily": "Inter",
                    "fontSize": 14,
                    "fontWeight": "400",
                    "fontStyle": "normal",
                    "lineHeight": 1.429,
                    "textAlign": "left",
                    "textAlignVertical": "top"
                  }
                ]
              },
              {
                "type": "frame",
                "name": "Div · Taylor Kim",
                "layout": "none",
                "layoutPosition": "absolute",
                "x": 13,
                "y": 33,
                "width": 326,
                "height": 20,
                "cornerRadius": 0,
                "children": [
                  {
                    "type": "text",
                    "name": "Div · Taylor Kim · Text",
                    "layoutPosition": "absolute",
                    "x": 0,
                    "y": 1,
                    "textGrowth": "auto",
                    "content": "Taylor Kim",
                    "fill": "#0A0A0A",
                    "fontFamily": "Inter",
                    "fontSize": 14,
                    "fontWeight": "500",
                    "fontStyle": "normal",
                    "lineHeight": 1.429,
                    "textAlign": "left",
                    "textAlignVertical": "top"
                  }
                ]
              }
            ]
          },
          {
            "type": "frame",
            "name": "Div",
            "layout": "none",
            "layoutPosition": "absolute",
            "x": 0,
            "y": 78,
            "width": 352,
            "height": 66,
            "cornerRadius": 10,
            "stroke": "#E5E5E5",
            "strokeWidth": 1,
            "strokeAlignment": "inner",
            "children": [
              {
                "type": "frame",
                "name": "Span · Due date",
                "layout": "none",
                "layoutPosition": "absolute",
                "x": 13,
                "y": 14,
                "width": 57.313,
                "height": 18,
                "cornerRadius": 0,
                "children": [
                  {
                    "type": "text",
                    "name": "Span · Due date · Text",
                    "layoutPosition": "absolute",
                    "x": 0,
                    "y": 0,
                    "textGrowth": "auto",
                    "content": "Due date",
                    "fill": "#737373",
                    "fontFamily": "Inter",
                    "fontSize": 14,
                    "fontWeight": "400",
                    "fontStyle": "normal",
                    "lineHeight": 1.429,
                    "textAlign": "left",
                    "textAlignVertical": "top"
                  }
                ]
              },
              {
                "type": "frame",
                "name": "Div · Jul 21, 2026",
                "layout": "none",
                "layoutPosition": "absolute",
                "x": 13,
                "y": 33,
                "width": 326,
                "height": 20,
                "cornerRadius": 0,
                "children": [
                  {
                    "type": "text",
                    "name": "Div · Jul 21, 2026 · Text",
                    "layoutPosition": "absolute",
                    "x": 0,
                    "y": 1,
                    "textGrowth": "auto",
                    "content": "Jul 21, 2026",
                    "fill": "#0A0A0A",
                    "fontFamily": "Inter",
                    "fontSize": 14,
                    "fontWeight": "500",
                    "fontStyle": "normal",
                    "lineHeight": 1.429,
                    "textAlign": "left",
                    "textAlignVertical": "top"
                  }
                ]
              }
            ]
          }
        ]
      },
      {
        "type": "frame",
        "name": "Div · dialog-footer",
        "layout": "none",
        "layoutPosition": "absolute",
        "x": 0,
        "y": 236,
        "width": 384,
        "height": 65,
        "cornerRadius": [
          0,
          0,
          14,
          14
        ],
        "fill": {
          "type": "color",
          "color": "#F5F5F580",
          "blendMode": "normal"
        },
        "stroke": "#E5E5E5",
        "strokeWidth": {
          "top": 1,
          "right": 0,
          "bottom": 0,
          "left": 0
        },
        "strokeAlignment": "inner",
        "children": [
          {
            "type": "frame",
            "name": "Button",
            "layout": "none",
            "layoutPosition": "absolute",
            "x": 179.063,
            "y": 17,
            "width": 67.578,
            "height": 32,
            "cornerRadius": 10,
            "fill": {
              "type": "color",
              "color": "#FFFFFF",
              "blendMode": "normal"
            },
            "stroke": "#A1A1A1",
            "strokeWidth": 1,
            "strokeAlignment": "inner",
            "effect": {
              "type": "shadow",
              "shadowType": "outer",
              "offset": {
                "x": 0,
                "y": 0
              },
              "blur": 0,
              "spread": 3,
              "color": "#A1A1A180"
            },
            "children": [
              {
                "type": "text",
                "name": "Button · Text",
                "layoutPosition": "absolute",
                "x": 11,
                "y": 7,
                "textGrowth": "auto",
                "content": "Cancel",
                "fill": "#0A0A0A",
                "fontFamily": "Inter",
                "fontSize": 14,
                "fontWeight": "500",
                "fontStyle": "normal",
                "lineHeight": 1.429,
                "textAlign": "center",
                "textAlignVertical": "middle"
              }
            ]
          },
          {
            "type": "frame",
            "name": "Button",
            "layout": "none",
            "layoutPosition": "absolute",
            "x": 254.641,
            "y": 17,
            "width": 113.359,
            "height": 32,
            "cornerRadius": 10,
            "fill": {
              "type": "color",
              "color": "#171717",
              "blendMode": "normal"
            },
            "children": [
              {
                "type": "text",
                "name": "Button · Text",
                "layoutPosition": "absolute",
                "x": 11,
                "y": 7,
                "textGrowth": "auto",
                "content": "Save changes",
                "fill": "#FAFAFA",
                "fontFamily": "Inter",
                "fontSize": 14,
                "fontWeight": "500",
                "fontStyle": "normal",
                "lineHeight": 1.429,
                "textAlign": "center",
                "textAlignVertical": "middle"
              }
            ]
          }
        ]
      },
      {
        "type": "frame",
        "name": "Button · dialog-close",
        "layout": "none",
        "layoutPosition": "absolute",
        "x": 348,
        "y": 8,
        "width": 28,
        "height": 28,
        "cornerRadius": 8,
        "children": [
          {
            "type": "frame",
            "name": "Svg",
            "layout": "none",
            "layoutPosition": "absolute",
            "x": 6,
            "y": 6,
            "width": 16,
            "height": 16,
            "cornerRadius": 0,
            "clip": true,
            "children": [
              {
                "type": "path",
                "name": "Path",
                "layoutPosition": "absolute",
                "x": 0,
                "y": 0,
                "width": 16,
                "height": 16,
                "fill": "#00000000",
                "stroke": "#0A0A0A",
                "strokeWidth": 1.333,
                "strokeLinecap": "round",
                "strokeLinejoin": "round",
                "geometry": "M18 6 6 18",
                "viewBox": [
                  0,
                  0,
                  24,
                  24
                ]
              },
              {
                "type": "path",
                "name": "Path",
                "layoutPosition": "absolute",
                "x": 0,
                "y": 0,
                "width": 16,
                "height": 16,
                "fill": "#00000000",
                "stroke": "#0A0A0A",
                "strokeWidth": 1.333,
                "strokeLinecap": "round",
                "strokeLinejoin": "round",
                "geometry": "m6 6 12 12",
                "viewBox": [
                  0,
                  0,
                  24,
                  24
                ]
              }
            ]
          }
        ]
      }
    ],
    "clip": false
  }
}
